rdkit_pypi-2022.9.5.dist-info/LICENSE.md
rdkit_pypi-2022.9.5.dist-info/RECORD
rdkit_pypi-2022.9.5.dist-info/WHEEL
rdkit_pypi-2022.9.5.dist-info/top_level.txt
rdkit_pypi-2022.9.5.dist-info/METADATA
rdkit/rdBase.so
rdkit/__init__.py
rdkit/RDConfig.py
rdkit/six.py
rdkit/license.txt
rdkit/RDPaths.py
rdkit/RDLogger.py
rdkit/TestRunner.py
rdkit/RDRandom.py
rdkit/DataManip/__init__.py
rdkit/DataManip/Metric/__init__.py
rdkit/DataManip/Metric/rdMetricMatrixCalc.so
rdkit/DataStructs/LazySignature.py
rdkit/DataStructs/BitEnsembleDb.py
rdkit/DataStructs/VectCollection.py
rdkit/DataStructs/BitUtils.py
rdkit/DataStructs/__init__.py
rdkit/DataStructs/TopNContainer.py
rdkit/DataStructs/cDataStructs.so
rdkit/DataStructs/BitEnsemble.py
rdkit/DataStructs/HierarchyVis.py
rdkit/ForceField/__init__.py
rdkit/ForceField/rdForceField.so
rdkit/Dbase/DbConnection.py
rdkit/Dbase/__init__.py
rdkit/Dbase/DbUtils.py
rdkit/Dbase/StorageUtils.py
rdkit/Dbase/DbInfo.py
rdkit/Dbase/DbResultSet.py
rdkit/Dbase/DbReport.py
rdkit/Dbase/DbModule.py
rdkit/utils/retest.txt
rdkit/utils/chemdraw_qax.py
rdkit/utils/chemdraw.py
rdkit/utils/fileutils.py
rdkit/utils/__init__.py
rdkit/utils/cactvs.py
rdkit/utils/chemutils.py
rdkit/utils/listutils.py
rdkit/utils/comhack.py
rdkit/utils/spiral.py
rdkit/Contrib/CMakeLists.txt
rdkit/Contrib/RxnRoleAssignment/identifyReactants.py
rdkit/Contrib/RxnRoleAssignment/__init__.py
rdkit/Contrib/RxnRoleAssignment/utils.py
rdkit/Contrib/RxnRoleAssignment/README.txt
rdkit/Contrib/CalcLigRMSD/README.md
rdkit/Contrib/CalcLigRMSD/CalcLigRMSD.py
rdkit/Contrib/Fastcluster/fastcluster.py
rdkit/Contrib/Fastcluster/clustered.tsv
rdkit/Contrib/Fastcluster/cdk2.smi
rdkit/Contrib/Fastcluster/centroid.tsv
rdkit/Contrib/Fastcluster/fp.tsv
rdkit/Contrib/Fastcluster/README.md
rdkit/Contrib/Fastcluster/clustered_parse.tsv
rdkit/Contrib/Fastcluster/testdata/cdk2.sdf
rdkit/Contrib/Fastcluster/testdata/sdf2smi.py
rdkit/Contrib/Fastcluster/testdata/converted.smi
rdkit/Contrib/M_Kossner/README
rdkit/Contrib/M_Kossner/Frames.py
rdkit/Contrib/M_Kossner/BaseFeatures_DIP2_NoMicrospecies.fdef
rdkit/Contrib/pzc/readme.md
